CogencisDataApiPy/CogencisDataApiPy.py
CogencisDataApiPy/__init__.py
CogencisDataApiPy-0.1.5.dist-info/METADATA
CogencisDataApiPy-0.1.5.dist-info/WHEEL
CogencisDataApiPy-0.1.5.dist-info/top_level.txt
CogencisDataApiPy-0.1.5.dist-info/RECORD
