Metadata-Version: 2.1
Name: CogencisDataApiPy
Version: 0.1.5
Summary: Simple interface to quickly to consume the Cogencis Data API in python environment. This package provides several functions for accessing historical market data and reference data
Home-page: https://cogencis.com
Author: Kannan M
Author-email: kannan.m@cogencis.com
License: MIT
Requires-Dist: requests
Requires-Dist: pandas
